{"time":"0128Z","data":[{"_id":"5db0e89d2149725063134ab7","id":4342754,"reg":"VQ-BWA","has_sig":false,"sig":-1,"icao":"4243E2","from":"LEMD Madrid Barajas, Spain","to":"UUEE Sheremetyevo, Moscow, Russia","gnd":false,"alt":36000,"lat":52.695831,"long":22.772289,"first_seen":"1467326978844","time":"0128Z","__v":0},{"_id":"5db0e8a02149725063135214","id":7405831,"reg":"HZ-AK29","has_sig":false,"sig":-1,"icao":"710107","from":"CYYZ Lester B. Pearson, Toronto, Canada","to":"OEJN King Abdulaziz, Jeddah, Saudi Arabia","gnd":false,"alt":35000,"lat":42.278141,"long":15.62237,"first_seen":"1467325730227","time":"0128Z","__v":0},{"_id":"5db0e89a214972506313437f","id":5023655,"reg":"EI-EFP","has_sig":false,"sig":-1,"icao":"4CA7A7","from":"LEBL Barcelona, Spain","to":"ESKN Stockholm Skavsta, Stockholm / Nyköping, Sweden","gnd":true,"alt":38000,"lat":55.8988,"long":14.36887,"first_seen":"1467327456971","time":"0128Z","__v":0},{"_id":"5db0e89c2149725063134731","id":7569526,"reg":"4X-ECF","has_sig":false,"sig":-1,"icao":"738076","from":"KEWR Newark Liberty, United States","to":"LLBG Ben Gurion, Tel Aviv, Israel","gnd":false,"alt":35000,"lat":42.682343,"long":20.1297,"first_seen":"1467327138266","time":"0128Z","__v":0},{"_id":"5db0e89a214972506313437a","id":12589547,"reg":"C-FJVE","has_sig":false,"sig":-1,"icao":"C019EB","from":null,"to":null,"gnd":false,"alt":37000,"lat":49.823364,"long":15.051992,"first_seen":"1467327474627","time":"0128Z","__v":0},{"_id":"5db0e84f2149725063127c94","id":4656458,"reg":"HA-FAW","has_sig":true,"sig":175,"icao":"470D4A","from":null,"to":null,"gnd":false,"alt":31000,"lat":47.017341,"long":7.155198,"first_seen":"1467335200073","time":"0128Z","__v":0},{"_id":"5db0e865214972506312b5ec","id":4574796,"reg":"OY-SRL","has_sig":false,"sig":-1,"icao":"45CE4C","from":"EDDK Cologne Bonn, Germany","to":"LIME Bergamo / Orio Al Serio, Italy","gnd":false,"alt":21925,"lat":46.454861,"long":9.42071,"first_seen":"1467334086318","time":"0128Z","__v":0},{"_id":"5db0e87f214972506312fb5b","id":5021993,"reg":null,"has_sig":true,"sig":122,"icao":"4CA129","from":null,"to":null,"gnd":false,"alt":39025,"lat":45.559433,"long":7.040696,"first_seen":"1467331893588","time":"0128Z","__v":0},{"_id":"5db0e876214972506312e468","id":5023827,"reg":"EI-EMK","has_sig":true,"sig":147,"icao":"4CA853","from":"LEPA Palma De Mallorca, Spain","to":"EDFH Frankfurt-Hahn, Hahn, Germany","gnd":false,"alt":38000,"lat":46.190061,"long":6.349068,"first_seen":"1467332713248","time":"0128Z","__v":0},{"_id":"5db0e868214972506312bd97","id":4342096,"reg":"VP-CPA","has_sig":false,"sig":-1,"icao":"424150","from":null,"to":null,"gnd":false,"alt":38000,"lat":45.167721,"long":10.02489,"first_seen":"1467333853285","time":"0128Z","__v":0},{"_id":"5db0e848214972506312692e","id":4656459,"reg":"HA-FAX","has_sig":false,"sig":-1,"icao":"470D4B","from":null,"to":null,"gnd":false,"alt":31000,"lat":49.471573,"long":8.16848,"first_seen":"1467335498824","time":"0128Z","__v":0},{"_id":"5db0e83a214972506312467b","id":4220834,"reg":"G-DHLH","has_sig":false,"sig":-1,"icao":"4067A2","from":null,"to":null,"gnd":false,"alt":18650,"lat":50.493484,"long":5.044532,"first_seen":"1467336106608","time":"0128Z","__v":0},{"_id":"5db0e88721497250631311db","id":3772901,"reg":"F-HEPF","has_sig":true,"sig":26,"icao":"3991E5","from":"LLBG Ben Gurion, Tel Aviv, Israel","to":"LFPG Charles de Gaulle, Paris, France","gnd":false,"alt":36000,"lat":45.464778,"long":12.532386,"first_seen":"1467330691488","time":"0128Z","__v":0},{"_id":"5db0e863214972506312b254","id":4999649,"reg":"YU-SPB","has_sig":true,"sig":27,"icao":"4C49E1","from":null,"to":null,"gnd":false,"alt":37000,"lat":49.79488,"long":6.165186,"first_seen":"1467334134161","time":"0128Z","__v":0},{"_id":"5db0e8862149725063130e47","id":131332,"reg":"CN-RGM","has_sig":true,"sig":28,"icao":"020104","from":"GMMN Mohammed V, Casablanca, Morocco","to":"UUEE Sheremetyevo, Moscow, Russia","gnd":false,"alt":38000,"lat":44.3535,"long":2.568316,"first_seen":"1467330846270","time":"0128Z","__v":0},{"_id":"5db0e86f214972506312d146","id":5023121,"reg":"EI-FMR","has_sig":true,"sig":34,"icao":"4CA591","from":"KJFK John F Kennedy, New York, United States","to":"LICJ Palermo / Punta Raisi, Italy","gnd":false,"alt":37050,"lat":48.474014,"long":-0.329097,"first_seen":"1467333307439","time":"0128Z","__v":0},{"_id":"5db0e862214972506312aeb8","id":4981280,"reg":"YU-ARA","has_sig":true,"sig":59,"icao":"4C0220","from":null,"to":null,"gnd":false,"alt":37000,"lat":48.244458,"long":-0.689681,"first_seen":"1467334220100","time":"0128Z","__v":0},{"_id":"5db0e83a214972506312468e","id":4508887,"reg":"OO-SFW","has_sig":true,"sig":16,"icao":"44CCD7","from":"FKYS Yaoundé Nsimalen, Cameroon","to":"EBBR Brussels, Belgium","gnd":false,"alt":40000,"lat":39.478729,"long":7.014532,"first_seen":"1467336073045","time":"0128Z","__v":0},{"_id":"5db0e8432149725063125d46","id":4195942,"reg":"G-BMRD","has_sig":true,"sig":24,"icao":"400666","from":null,"to":null,"gnd":false,"alt":26150,"lat":51.710541,"long":-0.936139,"first_seen":"1467335723012","time":"0128Z","__v":0},{"_id":"5db0e8462149725063126567","id":3958125,"reg":"D-AIKM","has_sig":true,"sig":28,"icao":"3C656D","from":"DNPO Port Harcourt, Nigeria","to":"EDDF Frankfurt am Main, Frankfurt-am-Main, Germany","gnd":false,"alt":38000,"lat":39.228407,"long":7.126831,"first_seen":"1467335602903","time":"0128Z","__v":0},{"_id":"5db0e87e214972506312f794","id":7634967,"reg":"OD-MEA","has_sig":false,"sig":-1,"icao":"748017","from":"OLBA Beirut Rafic Hariri, Lebanon","to":"LFPG Charles de Gaulle, Paris, France","gnd":false,"alt":40000,"lat":44.774597,"long":20.996769,"first_seen":"1467332030886","time":"0128Z","__v":0},{"_id":"5db0e88f2149725063132449","id":4196213,"reg":"G-VIIX","has_sig":false,"sig":-1,"icao":"400775","from":"OERK King Khaled, Riyadh, Saudi Arabia","to":"EGLL London Heathrow, United Kingdom","gnd":false,"alt":38000,"lat":38.513969,"long":22.246765,"first_seen":"1467330014063","time":"0128Z","__v":0},{"_id":"5db0e8452149725063126187","id":3754496,"reg":"F-GSQA","has_sig":true,"sig":72,"icao":"394A00","from":"WIII Soekarno-Hatta, Jakarta, Indonesia","to":"LFPG Charles de Gaulle, Paris, France","gnd":false,"alt":35975,"lat":44.457108,"long":26.647741,"first_seen":"1467335641840","time":"0128Z","__v":0},{"_id":"5db0e87e214972506312f79e","id":262216,"reg":"ET-AOR","has_sig":false,"sig":-1,"icao":"040048","from":"HAAB Bole, Addis Ababa, Ethiopia","to":"EBBR Brussels, Belgium","gnd":false,"alt":40000,"lat":38.302715,"long":22.446321,"first_seen":"1467332006808","time":"0128Z","__v":0},{"_id":"5db0e876214972506312e47e","id":4195770,"reg":"G-VIIB","has_sig":false,"sig":-1,"icao":"4005BA","from":"HKJK Jomo Kenyatta, Nairobi, Kenya","to":"EGLL London Heathrow, United Kingdom","gnd":false,"alt":38000,"lat":37.581947,"long":23.217813,"first_seen":"1467332623263","time":"0128Z","__v":0},{"_id":"5db0e84b21497250631270c9","id":5046592,"reg":"LX-OCV","has_sig":true,"sig":41,"icao":"4D0140","from":"UNNT Tolmachevo, Novosibirsk, Russia","to":"LIMC Malpensa, Milan, Italy","gnd":false,"alt":34000,"lat":57.290634,"long":36.440449,"first_seen":"1467335414652","time":"0128Z","__v":0},{"_id":"5db0e8a521497250631360a2","id":7864893,"reg":"B-KPQ","has_sig":false,"sig":-1,"icao":"78023D","from":"VHHH Chek Lap Kok, Hong Kong, Hong Kong","to":"LSZH Zürich, Zurich, Switzerland","gnd":false,"alt":36000,"lat":55.91803,"long":36.790379,"first_seen":"1467322135864","time":"0128Z","__v":0},{"_id":"5db0e848214972506312691c","id":4921472,"reg":"HB-JHG","has_sig":false,"sig":-1,"icao":"4B1880","from":"OOMS Muscat, Oman","to":"LSZH Zürich, Zurich, Switzerland","gnd":false,"alt":38000,"lat":41.496868,"long":35.544579,"first_seen":"1467335530027","time":"0128Z","__v":0},{"_id":"5db0e8aa2149725063136c1d","id":4921623,"reg":"HB-JNB","has_sig":false,"sig":-1,"icao":"4B1917","from":"VHHH Chek Lap Kok, Hong Kong, Hong Kong","to":"LSZH Zürich, Zurich, Switzerland","gnd":false,"alt":34000,"lat":56.985802,"long":37.118641,"first_seen":"1467314769324","time":"0128Z","__v":0},{"_id":"5db0e8532149725063128866","id":4921478,"reg":"HB-JHM","has_sig":false,"sig":-1,"icao":"4B1886","from":"VIDP Indira Gandhi, New Delhi, India","to":"LSZH Zürich, Zurich, Switzerland","gnd":false,"alt":36000,"lat":41.97065,"long":38.011189,"first_seen":"1467334992790","time":"0128Z","__v":0},{"_id":"5db0e89f2149725063134ec4","id":7864875,"reg":"B-KPL","has_sig":false,"sig":-1,"icao":"78022B","from":"VHHH Chek Lap Kok, Hong Kong, Hong Kong","to":"LIMC Malpensa, Milan, Italy","gnd":false,"alt":34575,"lat":56.14439,"long":51.566238,"first_seen":"1467325948838","time":"0128Z","__v":0},{"_id":"5db0e85c2149725063129f7d","id":3956466,"reg":"D-AGWR","has_sig":false,"sig":-1,"icao":"3C5EF2","from":"LTBJ Adnan Menderes, İzmir, Turkey","to":"EDDV Hannover, Germany","gnd":false,"alt":38000,"lat":41.82692,"long":23.520666,"first_seen":"1467334547898","time":"0128Z","__v":0},{"_id":"5db0e89a214972506313437c","id":434662,"reg":"A7-BFI","has_sig":false,"sig":-1,"icao":"06A1E6","from":"OTBD Doha, Qatar","to":"EGSS London Stansted, United Kingdom","gnd":false,"alt":34000,"lat":50.203701,"long":12.243743,"first_seen":"1467327468940","time":"0128Z","__v":0},{"_id":"5db0e8a02149725063135210","id":4458712,"reg":null,"has_sig":false,"sig":-1,"icao":"4408D8","from":null,"to":null,"gnd":false,"alt":31125,"lat":49.476559,"long":-52.190189,"first_seen":"1467325783603","time":"0128Z","__v":0},{"_id":"5db0e88a214972506313199f","id":11173213,"reg":"N775UA","has_sig":false,"sig":-1,"icao":"AA7D5D","from":"KEWR Newark Liberty, United States","to":"LIMC Malpensa, Milan, Italy","gnd":false,"alt":35975,"lat":49.654106,"long":-58.265842,"first_seen":"1467330419534","time":"0128Z","__v":0},{"_id":"5db0e8482149725063126924","id":10565437,"reg":"N178DN","has_sig":false,"sig":-1,"icao":"A1373D","from":"KTPA Tampa, United States","to":"LSZH Zürich, Zurich, Switzerland","gnd":false,"alt":36025,"lat":46.627487,"long":-51.659859,"first_seen":"1467335509574","time":"0128Z","__v":0},{"_id":"5db0e890214972506313285f","id":10664230,"reg":"N275AY","has_sig":false,"sig":-1,"icao":"A2B926","from":"KPHL Philadelphia, United States","to":"LIPZ Venezia / Tessera -  Marco Polo, Italy","gnd":false,"alt":38000,"lat":48.712189,"long":-56.661705,"first_seen":"1467329562732","time":"0128Z","__v":0},{"_id":"5db0e8892149725063131556","id":11179520,"reg":"N781UA","has_sig":false,"sig":-1,"icao":"AA9600","from":"KEWR Newark Liberty, United States","to":"LSZH Zürich, Zurich, Switzerland","gnd":false,"alt":34975,"lat":48.861008,"long":-59.027779,"first_seen":"1467330649863","time":"0128Z","__v":0},{"_id":"5db0e8a02149725063135213","id":11240619,"reg":"N841MH","has_sig":false,"sig":-1,"icao":"AB84AB","from":"SVMI Maiquetía (Simón Bolívar Internacional), Caracas, Venezuela","to":"KJFK John F Kennedy, New York, United States","gnd":false,"alt":35000,"lat":48.526199,"long":-57.99929,"first_seen":"1467325757977","time":"0128Z","__v":0},{"_id":"5db0e8a0214972506313522e","id":10548510,"reg":"N1608","has_sig":false,"sig":-1,"icao":"A0F51E","from":"KMIA Miami, United States","to":"EHAM Amsterdam Airport Schiphol, Netherlands","gnd":false,"alt":35025,"lat":48.738144,"long":-56.593605,"first_seen":"1467325296131","time":"0128Z","__v":0},{"_id":"5db0e8862149725063130e44","id":11158733,"reg":"N76062","has_sig":false,"sig":-1,"icao":"AA44CD","from":"KEWR Newark Liberty, United States","to":"LIPZ Venezia / Tessera -  Marco Polo, Italy","gnd":false,"alt":33000,"lat":47.059525,"long":-60.427139,"first_seen":"1467330863552","time":"0128Z","__v":0},{"_id":"5db0e861214972506312aadf","id":4958554,"reg":"TC-JJZ","has_sig":false,"sig":-1,"icao":"4BA95A","from":"KJFK John F Kennedy, New York, United States","to":"LTBA Atatürk, Istanbul, Turkey","gnd":false,"alt":32975,"lat":42.792297,"long":-68.227407,"first_seen":"1467334267178","time":"0128Z","__v":0},{"_id":"5db0e878214972506312e804","id":4921475,"reg":"HB-JHJ","has_sig":false,"sig":-1,"icao":"4B1883","from":"KORD Chicago O'Hare, United States","to":"LSZH Zürich, Zurich, Switzerland","gnd":false,"alt":37000,"lat":46.073685,"long":-78.204301,"first_seen":"1467332586451","time":"0128Z","__v":0},{"_id":"5db0e89d2149725063134adb","id":4577636,"reg":"OY-VKD","has_sig":true,"sig":24,"icao":"45D964","from":"LCLK Larnaca, Larnarca, Cyprus","to":"ENZV Stavanger Airport, Sola, Norway","gnd":false,"alt":33975,"lat":57.347981,"long":16.035786,"first_seen":"1467326633310","time":"0128Z","__v":0},{"_id":"5db0e84221497250631259d0","id":7569489,"reg":"4X-EHB","has_sig":false,"sig":-1,"icao":"738051","from":"LFPG Charles de Gaulle, Paris, France","to":"LLBG Ben Gurion, Tel Aviv, Israel","gnd":false,"alt":35000,"lat":37.504158,"long":22.214773,"first_seen":"1467335741325","time":"0128Z","__v":0},{"_id":"5db0e878214972506312e815","id":3146930,"reg":"I-NDMJ","has_sig":true,"sig":10,"icao":"3004B2","from":"LGIR Heraklion International Nikos Kazantzakis, Greece","to":"LIMC Malpensa, Milan, Italy","gnd":false,"alt":35000,"lat":32.138443,"long":-81.551624,"first_seen":"1467332529231","time":"0128Z","__v":0},{"_id":"5db0e8a3214972506313595f","id":3746542,"reg":"F-GKXO","has_sig":false,"sig":-1,"icao":"392AEE","from":"LFPG Charles de Gaulle, Paris, France","to":"LLBG Ben Gurion, Tel Aviv, Israel","gnd":false,"alt":29000,"lat":33.20343,"long":33.044513,"first_seen":"1467324060765","time":"0128Z","__v":0},{"_id":"5db0e8432149725063125d45","id":4958534,"reg":"TC-JJF","has_sig":false,"sig":-1,"icao":"4BA946","from":"KMIA Miami, United States","to":"LTBA Atatürk, Istanbul, Turkey","gnd":false,"alt":24475,"lat":26.253113,"long":-79.447998,"first_seen":"1467335723012","time":"0128Z","__v":0},{"_id":"5db0e879214972506312ec0c","id":4735850,"reg":"PH-BQC","has_sig":true,"sig":99,"icao":"48436A","from":"OMDB Dubai, United Arab Emirates","to":"EHAM Amsterdam Airport Schiphol, Netherlands","gnd":false,"alt":38000,"lat":44.440201,"long":26.287864,"first_seen":"1467332312121","time":"0128Z","__v":0},{"_id":"5db0e87e214972506312f798","id":4921482,"reg":"HB-JHQ","has_sig":true,"sig":11,"icao":"4B188A","from":"CYVR Vancouver, Canada","to":"LSZH Zürich, Zurich, Switzerland","gnd":false,"alt":35025,"lat":49.871924,"long":-109.642887,"first_seen":"1467332029089","time":"0128Z","__v":0},{"_id":"5db0e8832149725063130638","id":4220913,"reg":"G-TAWN","has_sig":true,"sig":13,"icao":"4067F1","from":null,"to":null,"gnd":false,"alt":38000,"lat":41.953766,"long":-8.554479,"first_seen":"1467331282569","time":"0128Z","__v":0},{"_id":"5db0e8a32149725063135961","id":4342780,"reg":"VQ-BWF","has_sig":false,"sig":-1,"icao":"4243FC","from":"LEMG Málaga, Spain","to":"UUEE Sheremetyevo, Moscow, Russia","gnd":false,"alt":35000,"lat":53.197899,"long":25.023951,"first_seen":"1467323976530","time":"0128Z","__v":0},{"_id":"5db0e8562149725063129025","id":7785835,"reg":"9V-SKK","has_sig":false,"sig":-1,"icao":"76CD6B","from":"WSSS Singapore Changi, Singapore","to":"LFPG Charles de Gaulle, Paris, France","gnd":false,"alt":38000,"lat":41.89436,"long":37.663052,"first_seen":"1467334876149","time":"0128Z","__v":0},{"_id":"5db0e87b214972506312effd","id":4341984,"reg":"VP-BUP","has_sig":false,"sig":-1,"icao":"4240E0","from":"UNBB Barnaul, Russia","to":"UUEE Sheremetyevo, Moscow, Russia","gnd":false,"alt":33875,"lat":57.11412,"long":71.506828,"first_seen":"1467332194293","time":"0128Z","__v":0},{"_id":"5db0e84f2149725063127c8c","id":12584271,"reg":"C-FCAG","has_sig":true,"sig":9,"icao":"C0054F","from":"CYYZ Lester B. Pearson, Toronto, Canada","to":"LIMC Malpensa, Milan, Italy","gnd":false,"alt":26725,"lat":43.999499,"long":-78.167725,"first_seen":"1467335211932","time":"0128Z","__v":0},{"_id":"5db0e8a121497250631355ad","id":4838249,"reg":"OK-TSI","has_sig":false,"sig":-1,"icao":"49D369","from":"LKPR Ruzyně, Prague, Czech Republic","to":"LLBG Ben Gurion, Tel Aviv, Israel","gnd":false,"alt":5100,"lat":32.151163,"long":34.602505,"first_seen":"1467324980520","time":"0128Z","__v":0},{"_id":"5db0e861214972506312aae3","id":12605504,"reg":"C-GHKX","has_sig":false,"sig":-1,"icao":"C05840","from":"CYUL Montreal / Pierre Elliott Trudeau, Montréal, Canada","to":"LIRF Leonardo Da Vinci (Fiumicino), Rome, Italy","gnd":false,"alt":28900,"lat":45.616928,"long":-71.239502,"first_seen":"1467334263115","time":"0128Z","__v":0},{"_id":"5db0e878214972506312e81b","id":4958544,"reg":"TC-JJP","has_sig":true,"sig":74,"icao":"4BA950","from":"LTBA Atatürk, Istanbul, Turkey","to":"KJFK John F Kennedy, New York, United States","gnd":false,"alt":19375,"lat":40.955169,"long":-74.221073,"first_seen":"1467332519278","time":"0128Z","__v":0},{"_id":"5db0e8a02149725063135221","id":4196233,"reg":"G-CPEV","has_sig":true,"sig":15,"icao":"400789","from":"LTAI Antalya, Turkey","to":"EGKK London Gatwick, United Kingdom","gnd":false,"alt":38000,"lat":49.813315,"long":4.540323,"first_seen":"1467325523351","time":"0128Z","__v":0},{"_id":"5db0e85e214972506312a354","id":4755877,"reg":"SP-ENF","has_sig":true,"sig":118,"icao":"4891A5","from":null,"to":null,"gnd":false,"alt":32025,"lat":45.244766,"long":9.736764,"first_seen":"1467334476866","time":"0128Z","__v":0},{"_id":"5db0e8962149725063133806","id":4198388,"reg":"G-FDZD","has_sig":true,"sig":45,"icao":"400FF4","from":"HESH Sharm El Sheikh, Sharm el-Sheikh, Egypt","to":"EGPF Glasgow, United Kingdom","gnd":false,"alt":17875,"lat":52.656052,"long":-2.571106,"first_seen":"1467328452086","time":"0128Z","__v":0},{"_id":"5db0e8a42149725063135ce5","id":4223003,"reg":"G-EZPF","has_sig":true,"sig":153,"icao":"40701B","from":"LCLK Larnaca, Larnarca, Cyprus","to":"EGKK London Gatwick, United Kingdom","gnd":false,"alt":36000,"lat":49.281502,"long":5.484274,"first_seen":"1467323584121","time":"0128Z","__v":0},{"_id":"5db0e8aa2149725063136c0e","id":172448,"reg":"TS-INA","has_sig":false,"sig":-1,"icao":"02A1A0","from":null,"to":null,"gnd":false,"alt":34000,"lat":57.26754,"long":25.440519,"first_seen":"1467316516989","time":"0128Z","__v":0},{"_id":"5db0e8a121497250631355a2","id":12613809,"reg":"C-GTSI","has_sig":false,"sig":-1,"icao":"C078B1","from":"CYUL Montreal / Pierre Elliott Trudeau, Montréal, Canada","to":"LFLL Lyon Saint-Exupéry, France","gnd":false,"alt":37000,"lat":46.538551,"long":-67.954147,"first_seen":"1467325177974","time":"0128Z","__v":0},{"_id":"5db0e848214972506312692b","id":3424598,"reg":"EC-LOB","has_sig":false,"sig":-1,"icao":"344156","from":null,"to":null,"gnd":false,"alt":3125,"lat":35.997391,"long":14.303398,"first_seen":"1467335503137","time":"0128Z","__v":0},{"_id":"5db0e8922149725063132c49","id":3934792,"reg":"D-ASXF","has_sig":false,"sig":-1,"icao":"3C0A48","from":"LTAU Kayseri Erkilet, Turkey","to":"EDDK Cologne Bonn, Germany","gnd":false,"alt":40000,"lat":50.235264,"long":11.199671,"first_seen":"1467329308340","time":"0128Z","__v":0},{"_id":"5db0e88721497250631311c5","id":4222356,"reg":"G-EZOO","has_sig":true,"sig":51,"icao":"406D94","from":"LEIB Ibiza, Spain","to":"EGKK London Gatwick, United Kingdom","gnd":false,"alt":28325,"lat":49.799815,"long":-1.112885,"first_seen":"1467330787380","time":"0128Z","__v":0},{"_id":"5db0e85221497250631284b2","id":4595510,"reg":"OH-LVI","has_sig":true,"sig":16,"icao":"461F36","from":"LTAI Antalya, Turkey","to":"EFHK Helsinki Vantaa, Finland","gnd":false,"alt":38000,"lat":41.24626,"long":29.633623,"first_seen":"1467335079728","time":"0128Z","__v":0},{"_id":"5db0e8372149725063123eab","id":4625100,"reg":"SX-DVL","has_sig":false,"sig":-1,"icao":"4692CC","from":"LIPX Verona / Villafranca, Italy","to":"LGIR Heraklion International Nikos Kazantzakis, Greece","gnd":false,"alt":24425,"lat":43.927551,"long":21.044439,"first_seen":"1467336212155","time":"0128Z","__v":0},{"_id":"5db0e87c214972506312f3e4","id":4949456,"reg":"TC-ANP","has_sig":false,"sig":-1,"icao":"4B85D0","from":"ESSA Stockholm-Arlanda, Stockholm, Sweden","to":"LTFJ Sabiha Gökçen, Istanbul, Turkey","gnd":true,"alt":37000,"lat":52.040371,"long":24.63888,"first_seen":"1467332050526","time":"0128Z","__v":0},{"_id":"5db0e84c21497250631274af","id":4967598,"reg":"TC-SEN","has_sig":true,"sig":46,"icao":"4BCCAE","from":"EDDN Nuremberg, Germany","to":"LTAI Antalya, Turkey","gnd":false,"alt":38425,"lat":48.434738,"long":13.948622,"first_seen":"1467335387574","time":"0128Z","__v":0},{"_id":"5db0e85c2149725063129f7e","id":3425944,"reg":"EC-MGE","has_sig":true,"sig":44,"icao":"344698","from":"LEBL Barcelona, Spain","to":"LLBG Ben Gurion, Tel Aviv, Israel","gnd":false,"alt":28125,"lat":40.995809,"long":4.173182,"first_seen":"1467334547898","time":"0128Z","__v":0},{"_id":"5db0e8a32149725063135948","id":4215976,"reg":"G-FDZF","has_sig":true,"sig":177,"icao":"4054A8","from":"LTBS Dalaman, Turkey","to":"EGTE Exeter, United Kingdom","gnd":false,"alt":32025,"lat":50.580496,"long":-0.950095,"first_seen":"1467324489095","time":"0128Z","__v":0},{"_id":"5db0e86c214972506312c986","id":9003530,"reg":"A6-EGI","has_sig":false,"sig":-1,"icao":"89620A","from":"KDFW Dallas Fort Worth, Dallas-Fort Worth, United States","to":"OMDB Dubai, United Arab Emirates","gnd":false,"alt":33000,"lat":51.279373,"long":1.623824,"first_seen":"1467333460189","time":"0128Z","__v":0},{"_id":"5db0e866214972506312b99d","id":4196232,"reg":"G-CPEU","has_sig":false,"sig":-1,"icao":"400788","from":"GVAC Amílcar Cabral, Espargos, Cape Verde","to":"EGKK London Gatwick, United Kingdom","gnd":false,"alt":14700,"lat":50.55452,"long":-0.500101,"first_seen":"1467333990052","time":"0128Z","__v":0},{"_id":"5db0e88a21497250631319a4","id":4958836,"reg":"TC-JST","has_sig":false,"sig":-1,"icao":"4BAA74","from":"LTBA Atatürk, Istanbul, Turkey","to":"OJAI Queen Alia, Amman, Jordan","gnd":false,"alt":32975,"lat":29.917969,"long":35.240425,"first_seen":"1467330414112","time":"0128Z","__v":0},{"_id":"5db0e862214972506312aeb5","id":4198007,"reg":"G-ZAPX","has_sig":true,"sig":16,"icao":"400E77","from":null,"to":null,"gnd":false,"alt":40025,"lat":42.203247,"long":4.997718,"first_seen":"1467334223162","time":"0128Z","__v":0},{"_id":"5db0e85b2149725063129b6e","id":4805256,"reg":"CS-TTH","has_sig":true,"sig":110,"icao":"495288","from":null,"to":null,"gnd":false,"alt":39025,"lat":43.019897,"long":0.724842,"first_seen":"1467334596648","time":"0128Z","__v":0},{"_id":"5db0e863214972506312b252","id":11286615,"reg":"N887FD","has_sig":true,"sig":38,"icao":"AC3857","from":"VHHH Chek Lap Kok, Hong Kong, Hong Kong","to":"KMEM Memphis, United States","gnd":false,"alt":35000,"lat":47.430725,"long":-119.526179,"first_seen":"1467334138099","time":"0128Z","__v":0},{"_id":"5db0e8452149725063126169","id":262406,"reg":"ET-ASL","has_sig":false,"sig":-1,"icao":"040106","from":"HAAB Bole, Addis Ababa, Ethiopia","to":"KIAD Washington Dulles, United States","gnd":false,"alt":35975,"lat":40.85527,"long":23.834167,"first_seen":"1467335681918","time":"0128Z","__v":0},{"_id":"5db0e8982149725063133c28","id":4221672,"reg":"G-TAWS","has_sig":false,"sig":-1,"icao":"406AE8","from":"HETB Taba, Egypt","to":"EGCC Manchester, United Kingdom","gnd":false,"alt":37975,"lat":48.410463,"long":9.406104,"first_seen":"1467328300085","time":"0128Z","__v":0}]}